datafiletoolbox/__init__.py
datafiletoolbox/PlotResults/SmartPlot.py
datafiletoolbox/SimulationInput/VFP.py
datafiletoolbox/SimulationInput/easyLoad.py
datafiletoolbox/SimulationInput/gridManipulation.py
datafiletoolbox/SimulationInput/keywords.py
datafiletoolbox/SimulationInput/propertyManipulation.py
datafiletoolbox/SimulationInput/readInput.py
datafiletoolbox/SimulationInput/read_VIPsss.py
datafiletoolbox/SimulationInput/read_VIPsss_noUnitMultiplier.py
datafiletoolbox/SimulationInput/simObject.py
datafiletoolbox/SimulationInput/todojunto.py
datafiletoolbox/SimulationInput/writeOutput.py
datafiletoolbox/SimulationResults/CSVSimResultNexusDesktopObject.py
datafiletoolbox/SimulationResults/__init__.py
datafiletoolbox/SimulationResults/eclObject.py
datafiletoolbox/SimulationResults/excelObject.py
datafiletoolbox/SimulationResults/h5Object.py
datafiletoolbox/SimulationResults/loader.py
datafiletoolbox/SimulationResults/mainObject.py
datafiletoolbox/SimulationResults/nexusObject.py
datafiletoolbox/SimulationResults/obshObject.py
datafiletoolbox/SimulationResults/odbcObject.py
datafiletoolbox/SimulationResults/resinsightObject.py
datafiletoolbox/SimulationResults/rsmObject.py
datafiletoolbox/SimulationResults/save_load.py
datafiletoolbox/SimulationResults/tableObject.py
datafiletoolbox/SimulationResults/vipObject.py
datafiletoolbox/SimulationResults/vipObject_withCSVsupport_OLD.py
datafiletoolbox/_Classes/EclSumLoader.py
datafiletoolbox/_Classes/Errors.py
datafiletoolbox/_Classes/Iterators.py
datafiletoolbox/_Classes/SimPandas.py
datafiletoolbox/_common/eclDATES.py
datafiletoolbox/_common/functions.py
datafiletoolbox/_common/inout.py
datafiletoolbox/_common/keywordsConversions.py
datafiletoolbox/_common/progressbar.py
datafiletoolbox/_common/readBinary.py
datafiletoolbox/_common/sharedVariables.py
datafiletoolbox/_common/slope.py
datafiletoolbox/_common/stringformat.py
datafiletoolbox/_common/unify.py
datafiletoolbox/_common/units.py
datafiletoolbox/_common/versions.py
datafiletoolbox-0.52.40.dist-info/LICENSE
datafiletoolbox-0.52.40.dist-info/METADATA
datafiletoolbox-0.52.40.dist-info/WHEEL
datafiletoolbox-0.52.40.dist-info/top_level.txt
datafiletoolbox-0.52.40.dist-info/RECORD
