Metadata-Version: 2.1
Name: datafiletoolbox
Version: 0.52.40
Summary: a set of utilities to deal with results from reservoir simulators and other sources of tabulated data.
Author-email: Martin Carlos Araya <martinaraya@gmail.com>
License: GNU GENERAL PUBLIC LICENSE
Classifier: Programming Language :: Python :: 3
Classifier: License :: OSI Approved :: GNU General Public License v3 (GPLv3)
Classifier: Operating System :: OS Independent
Requires-Python: >=3.7
License-File: LICENSE
Requires-Dist: numpy
Requires-Dist: pandas
Requires-Dist: matplotlib
Requires-Dist: seaborn
Requires-Dist: h5py
Requires-Dist: cwrap
Requires-Dist: openpyxl
Requires-Dist: xlsxwriter
